django_admin_global_sidebar/__init__.py
django_admin_global_sidebar/admin.py
django_admin_global_sidebar/apps.py
django_admin_global_sidebar/models.py
django_admin_global_sidebar/settings.py
django_admin_global_sidebar/tests.py
django_admin_global_sidebar/utils.py
django_admin_global_sidebar/views.py
django_admin_global_sidebar/migrations/__init__.py
django_admin_global_sidebar/static/django-admin-global-sidebar/css/django-admin-global-sidebar.css
django_admin_global_sidebar/static/django-admin-global-sidebar/js/django-admin-global-sidebar.js
django_admin_global_sidebar/templates/admin/base.html
django_admin_global_sidebar/templates/admin/base_site.html
django_admin_global_sidebar/templates/admin/django-admin-global-sidebar.html
django_admin_global_sidebar/templates/admin/login.html
django_admin_global_sidebar/templatetags/__init__.py
django_admin_global_sidebar/templatetags/django_admin_global_sidebar.py
django_admin_global_sidebar-0.2.3.dist-info/LICENSE
django_admin_global_sidebar-0.2.3.dist-info/METADATA
django_admin_global_sidebar-0.2.3.dist-info/WHEEL
django_admin_global_sidebar-0.2.3.dist-info/top_level.txt
django_admin_global_sidebar-0.2.3.dist-info/RECORD
