Metadata-Version: 2.1
Name: django-admin-global-sidebar
Version: 0.2.3
Summary: Provides a configurable left navigation bar for Django's admin site.
Home-page: UNKNOWN
Author: Li HaoRan
Maintainer: Li HaoRan
License: MIT
Keywords: django admin extentions,django admin global admin
Platform: UNKNOWN
Classifier: Development Status :: 5 - Production/Stable
Classifier: Intended Audience :: Developers
Classifier: Topic :: Software Development :: Libraries :: Python Modules
Classifier: License :: OSI Approved :: MIT License
Classifier: Programming Language :: Python :: 3
Classifier: Programming Language :: Python :: 3 :: Only
License-File: LICENSE
Requires-Dist: django
Requires-Dist: django-static-jquery3 >=5.0.0
Requires-Dist: django-static-fontawesome
Requires-Dist: magic-import
